pyspark_functions/__init__.py
pyspark_functions/dataframe.py
pyspark_functions/main.py
pyspark_functions-0.0.3.dist-info/METADATA
pyspark_functions-0.0.3.dist-info/WHEEL
pyspark_functions-0.0.3.dist-info/LICENSE
pyspark_functions-0.0.3.dist-info/RECORD
