Metadata-Version: 2.1
Name: pyspark-functions
Version: 0.0.3
Summary: 
Author: wiseupdata
Author-email: silvio.liborio@wiseupdata.com
Requires-Python: >=3.9,<4.0
Classifier: Programming Language :: Python :: 3
Classifier: Programming Language :: Python :: 3.9
Classifier: Programming Language :: Python :: 3.10
Classifier: Programming Language :: Python :: 3.11
Requires-Dist: pyspark (>=3.4.0,<4.0.0)
